Metadata-Version: 2.1
Name: chipshouter
Version: 1.1.0
Summary: ChipSHOUTER EMFI API
Home-page: http://www.ChipSHOUTER.com
Author: Colin O'Flynn
Author-email: coflynn@newae.com
License: GPLv3
Download-URL: https://github.com/newaetech/chipshouter
Platform: UNKNOWN
License-File: LICENSE
